{"Author":"","DateCreated":"2016-08-10T14:58:19.847863-07:00","TilesetFilename":"C:\\Users\\NicB\\Documents\\Visual Studio 2013\\Projects\\MapMaker\\tilea2.png","TileLength":32,"NextSector":0,"MapSize":"96, 96","AllMapGrids":[{"Id":0,"Corner":"0, 0","AllowsDriving":true,"AllowsFlying":true,"AllowsConstruction":true,"Sector":0,"Zone":0,"Tile":{"Corner":"0, 0","TilesetIndex":0}},{"Id":0,"Corner":"32, 0","AllowsDriving":true,"AllowsFlying":true,"AllowsConstruction":true,"Sector":0,"Zone":0,"Tile":{"Corner":"0, 0","TilesetIndex":0}},{"Id":0,"Corner":"64, 0","AllowsDriving":true,"AllowsFlying":true,"AllowsConstruction":true,"Sector":0,"Zone":0,"Tile":{"Corner":"0, 0","TilesetIndex":0}},{"Id":0,"Corner":"0, 32","AllowsDriving":true,"AllowsFlying":true,"AllowsConstruction":true,"Sector":0,"Zone":0,"Tile":{"Corner":"0, 0","TilesetIndex":0}},{"Id":0,"Corner":"32, 32","AllowsDriving":true,"AllowsFlying":true,"AllowsConstruction":false,"Sector":0,"Zone":0,"Tile":{"Corner":"128, 0","TilesetIndex":2}},{"Id":0,"Corner":"64, 32","AllowsDriving":true,"AllowsFlying":true,"AllowsConstruction":true,"Sector":0,"Zone":0,"Tile":{"Corner":"0, 0","TilesetIndex":0}},{"Id":0,"Corner":"0, 64","AllowsDriving":true,"AllowsFlying":true,"AllowsConstruction":true,"Sector":0,"Zone":0,"Tile":{"Corner":"0, 0","TilesetIndex":0}},{"Id":0,"Corner":"32, 64","AllowsDriving":true,"AllowsFlying":true,"AllowsConstruction":true,"Sector":0,"Zone":0,"Tile":{"Corner":"0, 0","TilesetIndex":0}},{"Id":0,"Corner":"64, 64","AllowsDriving":true,"AllowsFlying":true,"AllowsConstruction":true,"Sector":0,"Zone":0,"Tile":{"Corner":"0, 0","TilesetIndex":0}}]}
